algo_mid/__init__.py
algo_mid/ მონაცემთა სტრუქტურა სტეკი (Stack) ამოცანები რომლებიც იხსნება სტეკის საშუალებით/__init__.py
algo_mid/ მონაცემთა სტრუქტურა სტეკი (Stack) ამოცანები რომლებიც იხსნება სტეკის საშუალებით/implementingqueusingstack.py
algo_mid/ მონაცემთა სტრუქტურა სტეკი (Stack) ამოცანები რომლებიც იხსნება სტეკის საშუალებით/implementingstachusingquque.py
algo_mid/ მონაცემთა სტრუქტურა სტეკი (Stack) ამოცანები რომლებიც იხსნება სტეკის საშუალებით/minstack.py
algo_mid/ მონაცემთა სტრუქტურა სტეკი (Stack) ამოცანები რომლებიც იხსნება სტეკის საშუალებით/slide.txt
algo_mid/ მონაცემთა სტრუქტურა სტეკი (Stack) ამოცანები რომლებიც იხსნება სტეკის საშუალებით/validparenthesis.py
algo_mid/ამოცანები რომლებიც იხსნება ჰეშ ცხრილების (Hash Table) საშუალებით/__init__.py
algo_mid/ამოცანები რომლებიც იხსნება ჰეშ ცხრილების (Hash Table) საშუალებით/containsduplicate.py
algo_mid/ამოცანები რომლებიც იხსნება ჰეშ ცხრილების (Hash Table) საშუალებით/lru.py
algo_mid/ამოცანები რომლებიც იხსნება ჰეშ ცხრილების (Hash Table) საშუალებით/majorityelement.py
algo_mid/ამოცანები რომლებიც იხსნება ჰეშ ცხრილების (Hash Table) საშუალებით/slide.txt
algo_mid/ამოცანები რომლებიც იხსნება ჰეშ ცხრილების (Hash Table) საშუალებით/twosum.py
"algo_mid/გრაფი, გრაფის წარმოდგენა პროგრამაში; სიგანეში ძებნის ალგორითმი (Breadth-First Search, BFS)/__init__.py"
"algo_mid/გრაფი, გრაფის წარმოდგენა პროგრამაში; სიგანეში ძებნის ალგორითმი (Breadth-First Search, BFS)/adjList.py"
"algo_mid/გრაფი, გრაფის წარმოდგენა პროგრამაში; სიგანეში ძებნის ალგორითმი (Breadth-First Search, BFS)/adjMatrix.py"
"algo_mid/გრაფი, გრაფის წარმოდგენა პროგრამაში; სიგანეში ძებნის ალგორითმი (Breadth-First Search, BFS)/bfs.py"
"algo_mid/გრაფი, გრაფის წარმოდგენა პროგრამაში; სიგანეში ძებნის ალგორითმი (Breadth-First Search, BFS)/slide.txt"
"algo_mid/სიღრმეში ძებნის ალგორითმი (Depth-First Search, DFS), ციკლის პოვნა გრაფში (Cycle Detection) ტოპოლოგიური დალაგება (Topological Sort)/__init__.py"
algo_mid-0.1.5.dist-info/METADATA
algo_mid-0.1.5.dist-info/WHEEL
algo_mid-0.1.5.dist-info/top_level.txt
algo_mid-0.1.5.dist-info/RECORD
