Metadata-Version: 2.4
Name: algo_mid
Version: 0.1.5
Summary: Ghmerti ar gagvwiravs
Author: Bakuri Tchelidze
Author-email: bakuritchelidze@btu.com
Requires-Python: >=3.6
Dynamic: author
Dynamic: author-email
Dynamic: requires-python
Dynamic: summary
